permissions/__init__.py
permissions/urls.py
permissions/views.py
permissions/apps/__init__.py
permissions/apps/permissions_app/__init__.py
permissions/apps/permissions_app/permissions_form.py
permissions/apps/permissions_app/permissions_list.py
permissions/apps/permissions_app/users_access.py
permissions/management/__init__.py
permissions/management/commands/__init__.py
permissions/management/commands/sync_permissions.py
permissions/management/commands/users_permissions.py
permissions/migrations/0001_initial.py
permissions/migrations/__init__.py
permissions/models/__init__.py
permissions/models/permission.py
permissions/models/permission_queryset.py
core_permissions-0.3.dist-info/METADATA
core_permissions-0.3.dist-info/WHEEL
core_permissions-0.3.dist-info/top_level.txt
core_permissions-0.3.dist-info/RECORD
