Metadata-Version: 2.1
Name: core-permissions
Version: 0.3
Summary: Research CORE ERM - permissions module
Home-page: https://github.com/research-core/core-permissions
Author: Ricardo Ribeiro, Hugo Cachitas
Author-email: ricardojvr@gmail.com, hugo.cachitas@research.fchampalimaud.org
License: MIT
Platform: UNKNOWN
